{
  "aor": 0.001108976377952756,
  "aqi": 0.0009158968346456693,
  "bids_meta": {
    "EchoTime": 0.013,
    "RepetitionTime": 2.0,
    "SliceEncodingDirection": "k",
    "SliceTiming": [
      0.0,
      1.03,
      0.061,
      1.09,
      0.121,
      1.152,
      0.181,
      1.212,
      0.242,
      1.272,
      0.303,
      1.333,
      0.363,
      1.393,
      0.424,
      1.454,
      0.484,
      1.515,
      0.545,
      1.576,
      0.606,
      1.636,
      0.666,
      1.7,
      0.727,
      1.76,
      0.788,
      1.818,
      0.848,
      1.878,
      0.909,
      1.939,
      0.997
    ],
    "TaskName": "cuedSGT",
    "dataset": "ds000210",
    "modality": "bold",
    "run_id": 3,
    "subject_id": "01",
    "task_id": "cuedSGT"
  },
  "dummy_trs": 6,
  "dvars_nstd": 9.698132000355729,
  "dvars_std": 1.2093569302371545,
  "dvars_vstd": 0.9734534596442681,
  "efc": 0.4724898584356146,
  "fber": 304200.03125,
  "fd_mean": 0.06759035905960152,
  "fd_num": 3,
  "fd_perc": 1.1811023622047243,
  "fwhm_avg": 3.0831840125061816,
  "fwhm_x": 2.736453333333333,
  "fwhm_y": 3.1315466666666665,
  "fwhm_z": 3.381552037518545,
  "gcor": 0.0289566,
  "gsr_x": -0.0337725393474102,
  "gsr_y": 0.06827031075954437,
  "provenance": {
    "md5sum": "372156359d952fd5dc4a4d8722abbd00",
    "settings": {
      "fd_thres": 0.2,
      "testing": false
    },
    "software": "mriqc",
    "version": "22.0.0rc1",
    "webapi_port": null,
    "webapi_url": "https://mriqc.nimh.nih.gov/api/v1"
  },
  "size_t": 254,
  "size_x": 64,
  "size_y": 64,
  "size_z": 33,
  "snr": 3.4577632358434744,
  "spacing_tr": 2.0,
  "spacing_x": 3.75,
  "spacing_y": 3.75,
  "spacing_z": 3.8000006675720215,
  "summary_bg_k": 15.055165700971706,
  "summary_bg_mad": 11.884165803344748,
  "summary_bg_mean": 245.8013458251953,
  "summary_bg_median": 8.015748023986816,
  "summary_bg_n": 84356.0,
  "summary_bg_p05": 0.0,
  "summary_bg_p95": 1805.5117797851562,
  "summary_bg_stdv": 684.1654663085938,
  "summary_fg_k": 1.5423586848048565,
  "summary_fg_mad": 1080.230455548619,
  "summary_fg_mean": 4378.72998046875,
  "summary_fg_median": 4160.56494140625,
  "summary_fg_n": 21632.0,
  "summary_fg_p05": 2845.0588623046874,
  "summary_fg_p95": 6680.676464843751,
  "summary_fg_stdv": 1203.2254638671875,
  "tsnr": 142.7962843598798
}