{
  "aor": 0.002185736434108527,
  "aqi": 0.0015080188100775195,
  "bids_meta": {
    "EchoTime": 0.013,
    "RepetitionTime": 2.0,
    "SliceEncodingDirection": "k",
    "SliceTiming": [
      0.0,
      1.03,
      0.061,
      1.09,
      0.121,
      1.152,
      0.181,
      1.212,
      0.242,
      1.272,
      0.303,
      1.333,
      0.363,
      1.393,
      0.424,
      1.454,
      0.484,
      1.515,
      0.545,
      1.576,
      0.606,
      1.636,
      0.666,
      1.7,
      0.727,
      1.76,
      0.788,
      1.818,
      0.848,
      1.878,
      0.909,
      1.939,
      0.997
    ],
    "TaskName": "cuedSGT",
    "dataset": "ds000210",
    "modality": "bold",
    "run_id": 2,
    "subject_id": "05",
    "task_id": "cuedSGT"
  },
  "dummy_trs": 2,
  "dvars_nstd": 17.18111104264591,
  "dvars_std": 1.8651301603501946,
  "dvars_vstd": 0.9874695052529184,
  "efc": 0.4857819196409903,
  "fber": 128673.6953125,
  "fd_mean": 0.08358409965263924,
  "fd_num": 11,
  "fd_perc": 4.263565891472868,
  "fwhm_avg": 3.1559752854866843,
  "fwhm_x": 2.7449066666666666,
  "fwhm_y": 3.097440196929944,
  "fwhm_z": 3.6255789928634417,
  "gcor": 0.0664402,
  "gsr_x": -0.030055413022637367,
  "gsr_y": 0.06949424743652344,
  "provenance": {
    "md5sum": "40650f24e7e271454427e55ad71f8ffa",
    "settings": {
      "fd_thres": 0.2,
      "testing": false
    },
    "software": "mriqc",
    "version": "22.0.0rc1",
    "webapi_port": null,
    "webapi_url": "https://mriqc.nimh.nih.gov/api/v1"
  },
  "size_t": 258,
  "size_x": 64,
  "size_y": 64,
  "size_z": 33,
  "snr": 2.9583231880707452,
  "spacing_tr": 2.0,
  "spacing_x": 3.75,
  "spacing_y": 3.749999761581421,
  "spacing_z": 3.799999952316284,
  "summary_bg_k": 15.804768779213425,
  "summary_bg_mad": 17.779732869173554,
  "summary_bg_mean": 263.6005859375,
  "summary_bg_median": 11.992247581481934,
  "summary_bg_n": 80961.0,
  "summary_bg_p05": 0.0,
  "summary_bg_p95": 1992.7674560546875,
  "summary_bg_stdv": 754.6295166015625,
  "summary_fg_k": 2.4256072394536696,
  "summary_fg_mad": 1183.6566198083908,
  "summary_fg_mean": 4428.7353515625,
  "summary_fg_median": 4170.0966796875,
  "summary_fg_n": 23290.0,
  "summary_fg_p05": 2728.5976684570314,
  "summary_fg_p95": 7113.626855468749,
  "summary_fg_stdv": 1409.584716796875,
  "tsnr": 128.68039978388697
}